discord_gameserver_notifier/__init__.py
discord_gameserver_notifier/__main__.py
discord_gameserver_notifier/main.py
discord_gameserver_notifier/api/__init__.py
discord_gameserver_notifier/api/api_server.py
discord_gameserver_notifier/config/__init__.py
discord_gameserver_notifier/config/config_manager.py
discord_gameserver_notifier/database/__init__.py
discord_gameserver_notifier/database/database_manager.py
discord_gameserver_notifier/database/models.py
discord_gameserver_notifier/discord/__init__.py
discord_gameserver_notifier/discord/webhook_manager.py
discord_gameserver_notifier/discovery/__init__.py
discord_gameserver_notifier/discovery/game_wrappers.py
discord_gameserver_notifier/discovery/network_scanner.py
discord_gameserver_notifier/discovery/protocol_base.py
discord_gameserver_notifier/discovery/server_info_wrapper.py
discord_gameserver_notifier/discovery/protocols/__init__.py
discord_gameserver_notifier/discovery/protocols/aoe1.py
discord_gameserver_notifier/discovery/protocols/aoe2.py
discord_gameserver_notifier/discovery/protocols/avp2.py
discord_gameserver_notifier/discovery/protocols/battlefield2.py
discord_gameserver_notifier/discovery/protocols/cnc_generals.py
discord_gameserver_notifier/discovery/protocols/cod1.py
discord_gameserver_notifier/discovery/protocols/cod4.py
discord_gameserver_notifier/discovery/protocols/cod5.py
discord_gameserver_notifier/discovery/protocols/common.py
discord_gameserver_notifier/discovery/protocols/eldewrito.py
discord_gameserver_notifier/discovery/protocols/fear2.py
discord_gameserver_notifier/discovery/protocols/flatout2.py
discord_gameserver_notifier/discovery/protocols/halo1.py
discord_gameserver_notifier/discovery/protocols/jediknight.py
discord_gameserver_notifier/discovery/protocols/quake3.py
discord_gameserver_notifier/discovery/protocols/renegadex.py
discord_gameserver_notifier/discovery/protocols/source.py
discord_gameserver_notifier/discovery/protocols/ssc.py
discord_gameserver_notifier-0.3.1.dist-info/METADATA
discord_gameserver_notifier-0.3.1.dist-info/WHEEL
discord_gameserver_notifier-0.3.1.dist-info/entry_points.txt
discord_gameserver_notifier-0.3.1.dist-info/RECORD
